py_toolbelt/__init__.py
py_toolbelt/dict_toolbelt.py
py_toolbelt/float_toolbelt.py
py_toolbelt/functions_toolbelt.py
py_toolbelt/int_toolbelt.py
py_toolbelt/list_toolbelt.py
py_toolbelt/other_toolbelt.py
py_toolbelt/set_toolbelt.py
py_toolbelt/tuple_toolbelt.py
py_toolbelt-0.2.4.dist-info/LICENSE.txt
py_toolbelt-0.2.4.dist-info/METADATA
py_toolbelt-0.2.4.dist-info/WHEEL
py_toolbelt-0.2.4.dist-info/top_level.txt
py_toolbelt-0.2.4.dist-info/RECORD
