Metadata-Version: 2.1
Name: py-toolbelt
Version: 0.2.4
Summary: PyToolBelt - Extend your built-in methods.
Home-page: UNKNOWN
Author: Soami Charan
Author-email: charansoami@gmail.com
License: MIT
Keywords: python,PyToolBelt
Platform: UNKNOWN
Classifier: Development Status :: 3 - Alpha
Classifier: Intended Audience :: Education
Classifier: Programming Language :: Python :: 3
Requires-Dist: forbiddenfruit
Requires-Dist: jsondatabase
Requires-Dist: future
